{
  "version": 6,
  "include": ["common.json"],
  "configurePresets": [
    {
      "name": "Android-OpenGL",
      "displayName": "Android configuration using Qt6 and OpenGL",
      "generator": "Ninja",
      "binaryDir": "${sourceParentDir}/build/qt6-Android-OpenGL",
      "toolchainFile": "$penv{QT_ROOT_DIR}/lib/cmake/Qt6/qt.toolchain.cmake",
      "cacheVariables": {
        "CMAKE_BUILD_TYPE": "RelWithDebInfo",
        "CMAKE_POLICY_VERSION_MINIMUM": "3.19",
        "ANDROID_ABI": "$penv{ANDROID_ABI}",
        "MLN_WITH_OPENGL": "ON"
      }
    },
    {
      "name": "Android-Vulkan",
      "displayName": "Android configuration using Qt6 and Vulkan",
      "generator": "Ninja",
      "binaryDir": "${sourceParentDir}/build/qt6-Android-Vulkan",
      "toolchainFile": "$penv{QT_ROOT_DIR}/lib/cmake/Qt6/qt.toolchain.cmake",
      "cacheVariables": {
        "CMAKE_BUILD_TYPE": "RelWithDebInfo",
        "CMAKE_POLICY_VERSION_MINIMUM": "3.19",
        "ANDROID_ABI": "$penv{ANDROID_ABI}",
        "MLN_WITH_VULKAN": "ON"
      }
    },
    {
      "name": "Android-OpenGL-ccache",
      "displayName": "Android configuration using Qt6, OpenGL and ccache",
      "inherits": ["dev", "ccache", "Android-OpenGL"]
    },
    {
      "name": "Android-Vulkan-ccache",
      "displayName": "Android configuration using Qt6, Vulkan and ccache",
      "inherits": ["dev", "ccache", "Android-Vulkan"]
    },
    {
      "name": "Android-OpenGL-sccache",
      "displayName": "Android configuration using Qt6, OpenGL and sccache",
      "inherits": ["dev", "sccache", "Android-OpenGL"]
    },
    {
      "name": "Android-Vulkan-sccache",
      "displayName": "Android configuration using Qt6, Vulkan and sccache",
      "inherits": ["dev", "sccache", "Android-Vulkan"]
    }
  ],
  "buildPresets": [
    {
      "name": "Android-OpenGL",
      "displayName": "Android build using Qt6 and OpenGL",
      "configurePreset": "Android-OpenGL"
    },
    {
      "name": "Android-Vulkan",
      "displayName": "Android build using Qt6 and Vulkan",
      "configurePreset": "Android-Vulkan"
    },
    {
      "name": "Android-OpenGL-ccache",
      "displayName": "Android build using Qt6, OpenGL and ccache",
      "configurePreset": "Android-OpenGL-ccache"
    },
    {
      "name": "Android-Vulkan-ccache",
      "displayName": "Android build using Qt6, Vulkan and ccache",
      "configurePreset": "Android-Vulkan-ccache"
    },
    {
      "name": "Android-OpenGL-sccache",
      "displayName": "Android build using Qt6, OpenGL and sccache",
      "configurePreset": "Android-OpenGL-sccache"
    },
    {
      "name": "Android-Vulkan-sccache",
      "displayName": "Android build using Qt6, Vulkan and sccache",
      "configurePreset": "Android-Vulkan-sccache"
    }
  ],
  "packagePresets": [
    {
      "name": "Android-OpenGL",
      "displayName": "Android package using Qt6 and OpenGL",
      "configurePreset": "Android-OpenGL"
    },
    {
      "name": "Android-Vulkan",
      "displayName": "Android package using Qt6 and Vulkan",
      "configurePreset": "Android-Vulkan"
    },
    {
      "name": "Android-OpenGL-ccache",
      "displayName": "Android package using Qt6, OpenGL and ccache",
      "configurePreset": "Android-OpenGL-ccache"
    },
    {
      "name": "Android-Vulkan-ccache",
      "displayName": "Android package using Qt6, Vulkan and ccache",
      "configurePreset": "Android-Vulkan-ccache"
    },
    {
      "name": "Android-OpenGL-sccache",
      "displayName": "Android package using Qt6, OpenGL and sccache",
      "configurePreset": "Android-OpenGL-sccache"
    },
    {
      "name": "Android-Vulkan-sccache",
      "displayName": "Android package using Qt6, Vulkan and sccache",
      "configurePreset": "Android-Vulkan-sccache"
    }
  ],
  "workflowPresets": [
    {
      "name": "Android-OpenGL",
      "displayName": "Android workflow using Qt6 and OpenGL",
      "steps": [
        {
          "type": "configure",
          "name": "Android-OpenGL"
        },
        {
          "type": "build",
          "name": "Android-OpenGL"
        },
        {
          "type": "package",
          "name": "Android-OpenGL"
        }
      ]
    },
    {
      "name": "Android-Vulkan",
      "displayName": "Android workflow using Qt6 and Vulkan",
      "steps": [
        {
          "type": "configure",
          "name": "Android-Vulkan"
        },
        {
          "type": "build",
          "name": "Android-Vulkan"
        },
        {
          "type": "package",
          "name": "Android-Vulkan"
        }
      ]
    },
    {
      "name": "Android-OpenGL-ccache",
      "displayName": "Android workflow using Qt6, OpenGL and ccache",
      "steps": [
        {
          "type": "configure",
          "name": "Android-OpenGL-ccache"
        },
        {
          "type": "build",
          "name": "Android-OpenGL-ccache"
        },
        {
          "type": "package",
          "name": "Android-OpenGL-ccache"
        }
      ]
    },
    {
      "name": "Android-Vulkan-ccache",
      "displayName": "Android workflow using Qt6, Vulkan and ccache",
      "steps": [
        {
          "type": "configure",
          "name": "Android-Vulkan-ccache"
        },
        {
          "type": "build",
          "name": "Android-Vulkan-ccache"
        },
        {
          "type": "package",
          "name": "Android-Vulkan-ccache"
        }
      ]
    },
    {
      "name": "Android-OpenGL-sccache",
      "displayName": "Android workflow using Qt6, OpenGL and sccache",
      "steps": [
        {
          "type": "configure",
          "name": "Android-OpenGL-sccache"
        },
        {
          "type": "build",
          "name": "Android-OpenGL-sccache"
        },
        {
          "type": "package",
          "name": "Android-OpenGL-sccache"
        }
      ]
    },
    {
      "name": "Android-Vulkan-sccache",
      "displayName": "Android workflow using Qt6, Vulkan and sccache",
      "steps": [
        {
          "type": "configure",
          "name": "Android-Vulkan-sccache"
        },
        {
          "type": "build",
          "name": "Android-Vulkan-sccache"
        },
        {
          "type": "package",
          "name": "Android-Vulkan-sccache"
        }
      ]
    }
  ]
}
